sshconfig_to_ananta-2.1.1.dist-info/METADATA
sshconfig_to_ananta-2.1.1.dist-info/WHEEL
sshconfig_to_ananta-2.1.1.dist-info/entry_points.txt
sshconfig_to_ananta/__init__.py
sshconfig_to_ananta/__main__.py
sshconfig_to_ananta/ananta_host.py
sshconfig_to_ananta/main.py
sshconfig_to_ananta/ssh_config_converter.py
sshconfig_to_ananta-2.1.1.dist-info/RECORD
