Metadata-Version: 2.1
Name: sshconfig_to_ananta
Version: 2.1.1
Summary: Convert SSH config to Ananta hosts format (CSV or TOML)
Author: IceCodeNew, yzqzss
Project-URL: homepage, https://github.com/IceCodeNew/anata-no-minato.git
Project-URL: source, https://github.com/IceCodeNew/anata-no-minato.git
Project-URL: issues, https://github.com/IceCodeNew/anata-no-minato/issues
Requires-Python: >=3.10
Provides-Extra: toml
Requires-Dist: tomli-w>=1.2.0; extra == "toml"
